typedsql.py
typedsql-0.0.1.dev0.dist-info/METADATA
typedsql-0.0.1.dev0.dist-info/WHEEL
typedsql-0.0.1.dev0.dist-info/RECORD
